XWindowSystem_Screenshoter/__init__.py
XWindowSystem_Screenshoter/window_capture_async.py
XWindowSystem_Screenshoter/window_capture_sync.py
xwindowsystem_screenshoter-0.0.7.dist-info/METADATA
xwindowsystem_screenshoter-0.0.7.dist-info/WHEEL
xwindowsystem_screenshoter-0.0.7.dist-info/licenses/LICENSE
xwindowsystem_screenshoter-0.0.7.dist-info/RECORD
