Metadata-Version: 2.1
Name: XWindowSystem_Screenshoter
Version: 0.0.7
Summary: A simple use to capture a screenshot of single window in linux Systems
Project-URL: Repository, https://github.com/UR4N0-235/XWindowSystem_Screenshoter
Project-URL: Bug Tracker, https://github.com/UR4N0-235/XWindowSystem_Screenshoter/issues
Author-email: Matheus Verginio Fernandes <matheus.fernandes92.235@protonmail.com>
License: Copyright 2024 Matheus Verginio Fernandes
License-File: LICENSE
Keywords: Linux,XWindowSystem,screenshot,single window
Classifier: Development Status :: 4 - Beta
Classifier: License :: OSI Approved :: MIT License
Classifier: Operating System :: POSIX :: Linux
Classifier: Programming Language :: Python :: 3
Requires-Python: >=3.6
Requires-Dist: numpy>=1.26.1
Requires-Dist: xlib>=0.21
